Files/__init__.py
Files/config.py
Files/data_extractor.py
Files/genProcess.py
Files/invoice_item_description.py
Files/logger.py
Files/proteus_services_websocket.py
Files/proteus_websocket_listnear.py
Files/rasa_api.py
Files/rasa_id_interpreter.py
Files/read_cheque.py
Files/setup.py
Files/zip_capture.py
Proteus_Package-0.0.1.dist-info/LICENCE.txt
Proteus_Package-0.0.1.dist-info/METADATA
Proteus_Package-0.0.1.dist-info/WHEEL
Proteus_Package-0.0.1.dist-info/top_level.txt
Proteus_Package-0.0.1.dist-info/RECORD
