Metadata-Version: 2.1
Name: Proteus-Package
Version: 0.0.1
Summary: Proteustech Files
Author: Proteustech PVT. LTD.
Author-email: aniket.gadge@proteustech.in
Classifier: Programming Language :: Python :: 3
Classifier: License :: OSI Approved :: MIT License
Classifier: Operating System :: OS Independent
Requires-Python: >=3.6
License-File: LICENCE.txt
